objects/__init__.py
objects/errorset.py
objects/object.py
objects/utils.py
py_objects-0.1.1.dist-info/METADATA
py_objects-0.1.1.dist-info/WHEEL
py_objects-0.1.1.dist-info/RECORD
