Metadata-Version: 2.1
Name: py-objects
Version: 0.1.1
Summary: Better Than Enums
Home-page: https://github.com/odigity/py-objects/
Author: Ofer Nave
Author-email: odigity@gmail.com
Requires-Python: >=3.7,<4.0
Classifier: Programming Language :: Python :: 3
Classifier: Programming Language :: Python :: 3.7
Classifier: Programming Language :: Python :: 3.8
Classifier: Programming Language :: Python :: 3.9
Classifier: Programming Language :: Python :: 3.10
Classifier: Programming Language :: Python :: 3.11
Project-URL: Changelog, https://github.com/odigity/py-objects/blob/master/CHANGELOG.md
Project-URL: Documentation, https://py-objects.readthedocs.io/en/latest/
Project-URL: Repository, https://github.com/odigity/py-objects/
